music_score_creator
